cli.py
gitx.py
utils.py
tests/__init__.py
tests/gitx/__init__.py
tests/gitx/test_a.py
tests/gitx/test_amend.py
tests/gitx/test_ci.py
tests/gitx/test_clb.py
tests/gitx/test_co.py
tests/gitx/test_llg.py
tests/gitx/test_p.py
tests/gitx/test_pr.py
tests/gitx/test_st.py
tests/utils/__init__.py
tests/utils/test_call.py
tests/utils/test_platform.py
tests/utils/test_quote.py
tests/utils/test_start.py
git_x-0.3.202210210300.dist-info/LICENSE
git_x-0.3.202210210300.dist-info/METADATA
git_x-0.3.202210210300.dist-info/WHEEL
git_x-0.3.202210210300.dist-info/entry_points.txt
git_x-0.3.202210210300.dist-info/top_level.txt
git_x-0.3.202210210300.dist-info/RECORD
