Metadata-Version: 2.1
Name: git-x
Version: 0.3.202210210300
Summary: git-x - a set of handy git extensions.
Home-page: https://github.com/qszhuan/git-x
Author: Qingshan Zhuan
Author-email: zhuanqingshan@gmail.com
License: MIT
Project-URL: Bug Tracker, https://github.com/qszhuan/git-x/issues
Project-URL: Documentation, https://github.com/qszhuan/git-x/wiki
Project-URL: Source Code, https://github.com/qszhuan/git-x
Keywords: git extension,git,git-x
Classifier: Development Status :: 3 - Alpha
Classifier: Environment :: Console
Classifier: Intended Audience :: Developers
Classifier: Topic :: Utilities
Classifier: Topic :: Software Development
Classifier: Topic :: Terminals
Classifier: Topic :: Software Development :: Version Control
Classifier: Topic :: Software Development :: Version Control :: Git
Classifier: License :: OSI Approved :: MIT License
Classifier: Operating System :: OS Independent
Classifier: Programming Language :: Python :: 2.7
Classifier: Programming Language :: Python :: 3
Classifier: Programming Language :: Python :: 3.4
Classifier: Programming Language :: Python :: 3.5
Classifier: Programming Language :: Python :: 3.6
Classifier: Programming Language :: Python :: 3.7
Classifier: Programming Language :: Python :: 3.8
License-File: LICENSE
Requires-Dist: colorama
Requires-Dist: click
